MANIFEST.in
README.md
is_healthy.py
setup.cfg
setup.py
is_healthy.egg-info/PKG-INFO
is_healthy.egg-info/SOURCES.txt
is_healthy.egg-info/dependency_links.txt
is_healthy.egg-info/entry_points.txt
is_healthy.egg-info/not-zip-safe
is_healthy.egg-info/requires.txt
is_healthy.egg-info/top_level.txt