Metadata-Version: 1.1
Name: is-healthy
Version: 0.9.0
Summary: Mini healthcheck CLI
Home-page: https://github.com/carlskeide/is-healthy
Author: Carl Skeide
Author-email: carl@skeide.se
License: MIT
Download-URL: https://github.com/carlskeide/is-healthy/archive/0.9.0.tar.gz
Keywords: healthcheck
Platform: UNKNOWN
